{
  "last_updated": "2026-02-26T04:28:11.771380Z",
  "uob_prices_sgd": {
    "100g_cast_buy": 20972.0,
    "100g_cast_sell": 21310.0,
    "1kg_cast_buy": 209734.0,
    "1kg_cast_sell": 212277.0
  },
  "gold_spot_usd_per_oz": {
    "average": 5193.47,
    "sources": {
      "cnbc": 5193.21,
      "goldprice_org": 5193.735
    },
    "source_count": 2,
    "cross_validated": true
  },
  "usd_sgd_rate": {
    "average": 1.2645,
    "sources": {
      "exchangerate_api": 1.264127,
      "frankfurter": 1.2649
    },
    "source_count": 2,
    "cross_validated": true
  },
  "status": {
    "uob_success": true,
    "gold_spot_sources": 2,
    "forex_sources": 2,
    "gold_cross_validated": true,
    "forex_cross_validated": true
  },
  "errors": {},
  "calculated": {
    "spot_price_sgd_per_gram": 211.14,
    "spot_price_sgd_per_kg": 211140.74,
    "uob_1kg_premium_sgd": -1406.74,
    "uob_1kg_premium_percent": -0.67,
    "uob_spread_sgd": -2543.0,
    "uob_spread_percent": -1.21
  }
}